{
  "collectionName": "components_blocks_scrolling_galleries",
  "info": {
    "name": "Scrolling Gallery",
    "icon": "hand-point-right",
    "description": ""
  },
  "options": {},
  "attributes": {
    "items": {
      "type": "component",
      "repeatable": true,
      "component": "elements.gallery-item",
      "required": true,
      "min": 1
    },
    "layout_type": {
      "type": "enumeration",
      "enum": [
        "standard",
        "tall"
      ],
      "default": "standard",
      "required": true
    }
  }
}
